<?xml version="1.0" encoding="utf-8"?>
<!-- Copyright 2017, Grap
     License AGPL-3.0 or later (https://www.gnu.org/licenses/agpl). -->

<openerp><data>

        <record model="account.tax" id="account_tax_included_in_price">
            <field name="name">Demo - New Tax Included In Price (20%)</field>
            <field name="price_include">True</field>
            <field name="type">percent</field>
            <field name="amount">0.2</field>
        </record>

        <record model="account.tax" id="account_tax_excluded_in_price">
            <field name="name">Demo - New Tax Not Included In Price (10%)</field>
            <field name="price_include"></field>
            <field name="type">percent</field>
            <field name="amount">0.1</field>
        </record>

</data></openerp>